{
    "id": "ennu-kanum-yeshu-rajane",
    "title": "Ennu Kanum Yeshu Rajane",
    "composer": "Unknown",
    "lyricist": "Unknown",
    "language": "Malayalam",
    "duration": "4:00",
    "lyrics": {
        "manglish": {
            "para1": "Aa-Aa-Aa-Aa- ennu kanum yeshu rajane",
            "para2": "kaalamai kaalamai parannu povan kalamai",
            "para3": "rajathirajan varunnu vegam priyare!",
            "para4": "Kahalanadham kettidunna nalil",
            "para5": "Hallelujah! geetham padidume annu njan-",
            "para6": "Ennini njan chernnidum ponnumokham kanuvan",
            "para7": "Sobhayerum nattil njan poiduvan kalamai -",
            "para8": "Lokathil njanoru nindithanenkilum",
            "para9": "Mekhathil njanoru vathuvai vazhume-",
            "para10": "Yeshu rajan vannidum bhakthanmare cherkuvan",
            "para11": "Sworgathi sworgangalil vasam cheivan kalamai-",
            "para12": "Mulkirida dhariai kadannupoya priyane",
            "para13": "Pon kirida dhariai annu njan kanume-"
        },
        "malayalam": {
            "para1": "A_A_A_A_49u kazuM Eywurajen",
            "para2": "kalmay\\\\ kalmay\\\\ pR9uEpaka[ kalmay\\\\",
            "para3": "rajaXiraj[ vru9u EvgM `piyer‰",
            "para4": "! kahLnaxM Ek7ifu9 naLi}",
            "para5": "hEl|luy/a‰ gItM pafifuEm 19u qa[;_",
            "para6": "@ 49ini qa[ Ec{9ifuM epa9umuKM kazuva[",
            "para7": "EwaBEyRuM na7i} qa[ Epayifuva[ kalmay\\\\",
            "para8": "# Elak8i} qaenaru niºiten…iluM",
            "para9": "EmG8i} qaenaru vXuvay\\\\ vaSuem_",
            "para10": "$ Eywuraj[ v9ifuM Bk\\\\tÅaer Ec{6uva[",
            "para11": "sV{”aXisV{”NLi} vasMecy\\\\va[ kalmay\\\\_",
            "para12": "% mu]6irIfXariyay\\ kf9uEpay `piyen",
            "para13": "ep[kirIfXariyay\\ 19u qa[ kazuem_"
        }
    }
}